JoBase/__init__.cpython-310-x86_64-linux-gnu.so
JoBase/__init__.pyi
JoBase/audio/blip.wav
JoBase/audio/pickup.wav
JoBase/fonts/00.bin
JoBase/fonts/00.png
JoBase/fonts/01.bin
JoBase/fonts/01.png
JoBase/fonts/02.bin
JoBase/fonts/02.png
JoBase/fonts/03.bin
JoBase/fonts/03.png
JoBase/fonts/04.bin
JoBase/fonts/04.png
JoBase/images/coin.png
JoBase/images/enemy.png
JoBase/images/man.png
jobase.libs/libgcc_s-0cd532bd.so.1
jobase.libs/libstdc++-5d72f927.so.6.0.33
jobase-3.1.dist-info/METADATA
jobase-3.1.dist-info/WHEEL
jobase-3.1.dist-info/RECORD
jobase-3.1.dist-info/sboms/auditwheel.cdx.json
