Metadata-Version: 2.1
Name: JoBase
Version: 3.1
Summary: JoBase is a fast Python game library for beginner coders
Keywords: game engine learn beginner
Home-page: https://jobase.org
Author: Reuben Grey Ford
Author-email: <hello@jobase.org>
